reg_shared_lib/VERSION
reg_shared_lib/__init__.py
reg_shared_lib/api.py
reg_shared_lib/data.py
reg_shared_lib/py.typed
reg_shared_lib/tests.py
reg_shared_lib/di/__init__.py
reg_shared_lib/di/container.py
reg_shared_lib/pg/__init__.py
reg_shared_lib/pg/_fake_async_context.py
reg_shared_lib/pg/base.py
reg_shared_lib/pg/connection.py
reg_shared_lib/pg/helpers.py
reg_shared_lib/pg/repos.py
reg_shared_lib/pg/tests.py
reg_shared_lib-0.0.7.dist-info/LICENSE
reg_shared_lib-0.0.7.dist-info/METADATA
reg_shared_lib-0.0.7.dist-info/WHEEL
reg_shared_lib-0.0.7.dist-info/top_level.txt
reg_shared_lib-0.0.7.dist-info/RECORD
