Metadata-Version: 2.1
Name: reg-shared-lib
Version: 0.0.7
Summary: reg-shared-lib
Author-email: belegnar <belegnar@belegnar.ru>
License: MIT License
Project-URL: Homepage, https://reg.konvent.ru
Classifier: License :: OSI Approved :: MIT License
Classifier: Intended Audience :: Developers
Classifier: Programming Language :: Python :: 3
Classifier: Programming Language :: Python :: 3 :: Only
Classifier: Programming Language :: Python :: 3.11
Classifier: Programming Language :: Python :: 3.12
Classifier: Operating System :: OS Independent
Classifier: Development Status :: 5 - Production/Stable
Requires-Python: >=3.11
License-File: LICENSE
Requires-Dist: pytz
Requires-Dist: punq
